pulumi_docker_build/__init__.py
pulumi_docker_build/_enums.py
pulumi_docker_build/_inputs.py
pulumi_docker_build/_utilities.py
pulumi_docker_build/image.py
pulumi_docker_build/index.py
pulumi_docker_build/outputs.py
pulumi_docker_build/provider.py
pulumi_docker_build/pulumi-plugin.json
pulumi_docker_build/py.typed
pulumi_docker_build/config/__init__.py
pulumi_docker_build/config/__init__.pyi
pulumi_docker_build/config/vars.py
pulumi_docker_build-0.0.15.dist-info/METADATA
pulumi_docker_build-0.0.15.dist-info/WHEEL
pulumi_docker_build-0.0.15.dist-info/top_level.txt
pulumi_docker_build-0.0.15.dist-info/RECORD
